{"title":"UEL.2013.16F.2leg.(21 feb).Benfica.v.Bayer.720p","uid":8178476,"size":3161444592,"categoryP":"video","categoryS":"hd___tv_shows","magnet":"?xt=urn:btih:047dd582c3764022d40834e90e7d791c81661dcd&amp;dn=UEL.2013.16F.2leg.%2821+feb%29.Benfica.v.Bayer.720p&amp;tr=udp%3A%2F%2Ftracker.openbittorrent.com%3A80&amp;tr=udp%3A%2F%2Fopen.demonii.com%3A1337&amp;tr=udp%3A%2F%2Ftracker.coppersurfer.tk%3A6969&amp;tr=udp%3A%2F%2Fexodus.desync.com%3A6969","seeders":1,"leechers":0,"uploader":"Nepotu","files":1,"time":1361576083,"description":"UEFA Europa League 2012-2013\n-------------------------------\nLast 32 - 21 february 2013 - Second leg\n \n\nSL BENFICA LISBON (POR) - BAYER 04 LEVERKUSEN (GER) (courtesy of NTV+ - RUS)\n\n\n\n\nVideo: 720p\n\n\n\nCredit: Bagga","torrent":{"xt":"urn:btih:047dd582c3764022d40834e90e7d791c81661dcd","amp;dn":"UEL.2013.16F.2leg.%2821+feb%29.Benfica.v.Bayer.720p","amp;tr":["udp%3A%2F%2Ftracker.openbittorrent.com%3A80","udp%3A%2F%2Fopen.demonii.com%3A1337","udp%3A%2F%2Ftracker.coppersurfer.tk%3A6969","udp%3A%2F%2Fexodus.desync.com%3A6969"],"infoHash":"047dd582c3764022d40834e90e7d791c81661dcd","infoHashBuffer":{"type":"Buffer","data":[4,125,213,130,195,118,64,34,212,8,52,233,14,125,121,28,129,102,29,205]},"announce":[],"urlList":[]}}