{"title":"Party Hardcore Gone Crazy 2","uid":10310698,"size":2955450805,"categoryP":"porn","categoryS":"movies","magnet":"?xt=urn:btih:084cb489472f4b5b6b84c4d677ccf94fd9de8eb8&amp;dn=Party+Hardcore+Gone+Crazy+2&amp;tr=udp%3A%2F%2Ftracker.openbittorrent.com%3A80&amp;tr=udp%3A%2F%2Fopen.demonii.com%3A1337&amp;tr=udp%3A%2F%2Ftracker.coppersurfer.tk%3A6969&amp;tr=udp%3A%2F%2Fexodus.desync.com%3A6969","seeders":1,"leechers":0,"uploader":"digital_ripper","files":1,"time":1402176291,"description":"screens\n\n &lt;a href=&quot;\nhttp://www.mypornimage.com/adultimage/TDy&quot; rel=&quot;nofollow&quot; target=&quot;_NEW&quot;&gt;\nhttp://www.mypornimage.com/adultimage/TDy&lt;/a&gt; &lt;a href=&quot;\nhttp://www.mypornimage.com/adultimage/TD6&quot; rel=&quot;nofollow&quot; target=&quot;_NEW&quot;&gt;\nhttp://www.mypornimage.com/adultimage/TD6&lt;/a&gt;\n\n\n~~~~~~~~~~~~~~~~~~~~~~~~~~~~~~~~~~~~~~~~~~~~~~~~~~~~~~~~~~~~~~~~~~~~~~~~~~~~~~~\n\n                       ````````````````````````````````\n                   Watch this porn videos at hardsexseetube\n~~~~~~~~~~~~~~~~~~~~~~~~~~~~~~~~~~~~~~~~~~~~~~~~~~~~~~~~~~~~~~~~~~~~~~~~~~~~~~~","torrent":{"xt":"urn:btih:084cb489472f4b5b6b84c4d677ccf94fd9de8eb8","amp;dn":"Party+Hardcore+Gone+Crazy+2","amp;tr":["udp%3A%2F%2Ftracker.openbittorrent.com%3A80","udp%3A%2F%2Fopen.demonii.com%3A1337","udp%3A%2F%2Ftracker.coppersurfer.tk%3A6969","udp%3A%2F%2Fexodus.desync.com%3A6969"],"infoHash":"084cb489472f4b5b6b84c4d677ccf94fd9de8eb8","infoHashBuffer":{"type":"Buffer","data":[8,76,180,137,71,47,75,91,107,132,196,214,119,204,249,79,217,222,142,184]},"announce":[],"urlList":[]}}