{"title":"[gg]_Tokyo_Ravens_-_09_[32468CEB].mkv","uid":9293864,"size":345244193,"categoryP":"video","categoryS":"hd___tv_shows","magnet":"?xt=urn:btih:0f4de4697ae0156b0620117b7295ce6b296a084c&amp;dn=%5Bgg%5D_Tokyo_Ravens_-_09_%5B32468CEB%5D.mkv&amp;tr=udp%3A%2F%2Ftracker.openbittorrent.com%3A80&amp;tr=udp%3A%2F%2Fopen.demonii.com%3A1337&amp;tr=udp%3A%2F%2Ftracker.coppersurfer.tk%3A6969&amp;tr=udp%3A%2F%2Fexodus.desync.com%3A6969","seeders":1,"leechers":0,"uploader":"darkj6","files":1,"time":1386131878,"description":" ______   _______  ______    ___   _      ___  --------|\n|      | |   _   ||    _ |  |   | | |    |   ||   |----|    \n|  _    ||  |_|  ||   | ||  |   |_| |    |   ||   |___ \n| | |   ||       ||   |_||_ |      _|    |   ||    _  |\n| |_|   ||       ||    __  ||     |_  ___|   ||   | | |\n|       ||   _   ||   |  | ||    _  ||       ||   |_| |\n|______| |__| |__||___|  |_||___| |_||_______||_______|","torrent":{"xt":"urn:btih:0f4de4697ae0156b0620117b7295ce6b296a084c","amp;dn":"%5Bgg%5D_Tokyo_Ravens_-_09_%5B32468CEB%5D.mkv","amp;tr":["udp%3A%2F%2Ftracker.openbittorrent.com%3A80","udp%3A%2F%2Fopen.demonii.com%3A1337","udp%3A%2F%2Ftracker.coppersurfer.tk%3A6969","udp%3A%2F%2Fexodus.desync.com%3A6969"],"infoHash":"0f4de4697ae0156b0620117b7295ce6b296a084c","infoHashBuffer":{"type":"Buffer","data":[15,77,228,105,122,224,21,107,6,32,17,123,114,149,206,107,41,106,8,76]},"announce":[],"urlList":[]}}