{"title":"Zulu.2013.BRRip.XViD.AC3.ReLeNTLesS","uid":9943599,"size":1139852855,"categoryP":"video","categoryS":"movies","magnet":"?xt=urn:btih:102dfaf5f39fd9b62d07e616112e6427a88383f1&amp;dn=Zulu.2013.BRRip.XViD.AC3.ReLeNTLesS&amp;tr=udp%3A%2F%2Ftracker.openbittorrent.com%3A80&amp;tr=udp%3A%2F%2Fopen.demonii.com%3A1337&amp;tr=udp%3A%2F%2Ftracker.coppersurfer.tk%3A6969&amp;tr=udp%3A%2F%2Fexodus.desync.com%3A6969","seeders":1,"leechers":0,"uploader":"sceneline","files":5,"time":1397284127,"description":"-\nsignup open at Scenetime !!!\n\nFor the sake of sharing, Please seed as long as you can\n\n\n\n ............ NFO .............\n-\t\nFor more info about this show check NFO file\n-","torrent":{"xt":"urn:btih:102dfaf5f39fd9b62d07e616112e6427a88383f1","amp;dn":"Zulu.2013.BRRip.XViD.AC3.ReLeNTLesS","amp;tr":["udp%3A%2F%2Ftracker.openbittorrent.com%3A80","udp%3A%2F%2Fopen.demonii.com%3A1337","udp%3A%2F%2Ftracker.coppersurfer.tk%3A6969","udp%3A%2F%2Fexodus.desync.com%3A6969"],"infoHash":"102dfaf5f39fd9b62d07e616112e6427a88383f1","infoHashBuffer":{"type":"Buffer","data":[16,45,250,245,243,159,217,182,45,7,230,22,17,46,100,39,168,131,131,241]},"announce":[],"urlList":[]}}