{"title":"1By-Day.13.09.30.Michelle.Impress.Our.Imaginations.XXX.IMAGESET-","uid":8979501,"size":24739278,"categoryP":"porn","categoryS":"other","magnet":"?xt=urn:btih:13c47c9190fe41eaa01247e4c7f3fc2a951f2a4c&amp;dn=1By-Day.13.09.30.Michelle.Impress.Our.Imaginations.XXX.IMAGESET-&amp;tr=udp%3A%2F%2Ftracker.openbittorrent.com%3A80&amp;tr=udp%3A%2F%2Fopen.demonii.com%3A1337&amp;tr=udp%3A%2F%2Ftracker.coppersurfer.tk%3A6969&amp;tr=udp%3A%2F%2Fexodus.desync.com%3A6969","seeders":1,"leechers":0,"uploader":"Drarbg","files":103,"time":1380524718,"description":"1By-Day.com_13.09.30.Michelle.Impress.Our.Imaginations.XXX.IMAGESET-PAYiSO\n","torrent":{"xt":"urn:btih:13c47c9190fe41eaa01247e4c7f3fc2a951f2a4c","amp;dn":"1By-Day.13.09.30.Michelle.Impress.Our.Imaginations.XXX.IMAGESET-","amp;tr":["udp%3A%2F%2Ftracker.openbittorrent.com%3A80","udp%3A%2F%2Fopen.demonii.com%3A1337","udp%3A%2F%2Ftracker.coppersurfer.tk%3A6969","udp%3A%2F%2Fexodus.desync.com%3A6969"],"infoHash":"13c47c9190fe41eaa01247e4c7f3fc2a951f2a4c","infoHashBuffer":{"type":"Buffer","data":[19,196,124,145,144,254,65,234,160,18,71,228,199,243,252,42,149,31,42,76]},"announce":[],"urlList":[]}}