{"title":"[Lethal Hardcore] Your Mom Tossed My Salad 17 (2016)","uid":14838567,"size":2976387983,"categoryP":"porn","categoryS":"movies","magnet":"?xt=urn:btih:17828c9530e2d3f86f805f1beb07c27040ad345a&amp;dn=%5BLethal+Hardcore%5D+Your+Mom+Tossed+My+Salad+17+%282016%29&amp;tr=udp%3A%2F%2Ftracker.leechers-paradise.org%3A6969&amp;tr=udp%3A%2F%2Fzer0day.ch%3A1337&amp;tr=udp%3A%2F%2Fopen.demonii.com%3A1337&amp;tr=udp%3A%2F%2Ftracker.coppersurfer.tk%3A6969&amp;tr=udp%3A%2F%2Fexodus.desync.com%3A6969","seeders":1,"leechers":1,"uploader":"SudoSu","files":6,"time":1465354062,"description":"http://youpornbook.com\r\n\r\n-------------------------\r\n ... : Screenshots : ... \r\n-------------------------\r\n \nhttp://imgscorpion.com/?v=837770 \nhttp://imgscorpion.com/?v=531447 \nhttp://imgscorpion.com/?v=212771 \nhttp://imgscorpion.com/?v=139201 \nhttp://imgscorpion.com/?v=905037 \nhttp://imgscorpion.com/?v=321422\r\n\r\nStarring:\r\n\r\nSarah Vandella, Cherie DeVille, Stevie Lix, \r\nSavannah Fyre \r\n\r\n\r\nDescription :\r\n\r\nRomeo almost got fired for dicking around at work until he offered to let his manager Cherie lick around his butthole before he went balls deep in her pussy until she had multiple orgasms. Sarah knew Sonny was the right applicant for the job when he looked her straight in the eye, so she put her tongue deep in his brown eye and said &quot;You're Hired!&quot;. Savannah felt terrible when her son ditched his best friend Brad again, so she cheered him up with some kind words, a rim job and some poon tang! Stevie Lix helped Damon work out his glutes at the gym by burying her tongue in his asshole, then he pounded her pussy into oblivion!!\r\n\r\nMore exclusive porn at:  https://thepiratebay.se/user/SudoSu/","torrent":{"xt":"urn:btih:17828c9530e2d3f86f805f1beb07c27040ad345a","amp;dn":"%5BLethal+Hardcore%5D+Your+Mom+Tossed+My+Salad+17+%282016%29","amp;tr":["udp%3A%2F%2Ftracker.leechers-paradise.org%3A6969","udp%3A%2F%2Fzer0day.ch%3A1337","udp%3A%2F%2Fopen.demonii.com%3A1337","udp%3A%2F%2Ftracker.coppersurfer.tk%3A6969","udp%3A%2F%2Fexodus.desync.com%3A6969"],"infoHash":"17828c9530e2d3f86f805f1beb07c27040ad345a","infoHashBuffer":{"type":"Buffer","data":[23,130,140,149,48,226,211,248,111,128,95,27,235,7,194,112,64,173,52,90]},"announce":[],"urlList":[]}}