{"title":"Kath and Kim US S01E12 HDTV XviD-LOL [eztv]","uid":4707112,"size":182705410,"categoryP":"video","categoryS":"tv_shows","magnet":"?xt=urn:btih:1a2b24b538aaee4af803397c1ea8332e9d48c5a6&amp;dn=Kath+and+Kim+US+S01E12+HDTV+XviD-LOL+%5Beztv%5D&amp;tr=udp%3A%2F%2Ftracker.openbittorrent.com%3A80&amp;tr=udp%3A%2F%2Fopen.demonii.com%3A1337&amp;tr=udp%3A%2F%2Ftracker.coppersurfer.tk%3A6969&amp;tr=udp%3A%2F%2Fexodus.desync.com%3A6969","seeders":1,"leechers":1,"uploader":"eztv","files":1,"time":1233891229,"description":"#EZTV @ EFNet -&gt; http://eztv.it/\n\nWant to help us out? BitCoin: 1Fw4sRdZYFwULfeE7oQ91GLYKy8j5EcuFW","torrent":{"xt":"urn:btih:1a2b24b538aaee4af803397c1ea8332e9d48c5a6","amp;dn":"Kath+and+Kim+US+S01E12+HDTV+XviD-LOL+%5Beztv%5D","amp;tr":["udp%3A%2F%2Ftracker.openbittorrent.com%3A80","udp%3A%2F%2Fopen.demonii.com%3A1337","udp%3A%2F%2Ftracker.coppersurfer.tk%3A6969","udp%3A%2F%2Fexodus.desync.com%3A6969"],"infoHash":"1a2b24b538aaee4af803397c1ea8332e9d48c5a6","infoHashBuffer":{"type":"Buffer","data":[26,43,36,181,56,170,238,74,248,3,57,124,30,168,51,46,157,72,197,166]},"announce":[],"urlList":[]}}