{"title":"Anthrax - For All Kings (Limited Edition 2CD) 2016","uid":13700400,"size":197901026,"categoryP":"audio","categoryS":"music","magnet":"?xt=urn:btih:27ac8930872b8393f61ca0613375666ac8889806&amp;dn=Anthrax+-+For+All+Kings+%28Limited+Edition+2CD%29+2016&amp;tr=udp%3A%2F%2Ftracker.leechers-paradise.org%3A6969&amp;tr=udp%3A%2F%2Fzer0day.ch%3A1337&amp;tr=udp%3A%2F%2Fopen.demonii.com%3A1337&amp;tr=udp%3A%2F%2Ftracker.coppersurfer.tk%3A6969&amp;tr=udp%3A%2F%2Fexodus.desync.com%3A6969","seeders":1,"leechers":0,"uploader":"RoffeTheCoolMan","files":18,"time":1456766016,"description":"Anthrax – For All Kings (Limited Edition 2CD) (2016) [MP3]\r\n\r\nBand: Anthrax\r\n\r\nGenre: Thrash Metal\r\nCountry: USA\r\nYear: 2016\r\nAudio codec: MP3\r\nRiptype: tracks\r\nBitrate: 320 kbps\r\nSite:\nTracklist:\r\nCD1 – 00:59:39\r\n01. Impaled\r\n02. You Gotta Believe\r\n03. Monster at the End\r\n04. For All Kings\r\n05. Breathing Lightning\r\n06. Breathing Out\r\n07. Suzerain\r\n08. Evil Twin\r\n09. Blood Eagle Wings\r\n10. Defend / Avenge\r\n11. All of Them Thieves\r\n12. This Battle Chose Us\r\n13. Zero Tolerance\r\n\r\nCD2 – 00:22:12\r\n01. Fight ‘Em ’til You Can’t (Live)\r\n02. A.I.R. (Live)\r\n03. Caught in a Mosh (Live)\r\n04. Madhouse (Live)","torrent":{"xt":"urn:btih:27ac8930872b8393f61ca0613375666ac8889806","amp;dn":"Anthrax+-+For+All+Kings+%28Limited+Edition+2CD%29+2016","amp;tr":["udp%3A%2F%2Ftracker.leechers-paradise.org%3A6969","udp%3A%2F%2Fzer0day.ch%3A1337","udp%3A%2F%2Fopen.demonii.com%3A1337","udp%3A%2F%2Ftracker.coppersurfer.tk%3A6969","udp%3A%2F%2Fexodus.desync.com%3A6969"],"infoHash":"27ac8930872b8393f61ca0613375666ac8889806","infoHashBuffer":{"type":"Buffer","data":[39,172,137,48,135,43,131,147,246,28,160,97,51,117,102,106,200,136,152,6]},"announce":[],"urlList":[]}}