{"title":"[BigTitsInUniform.com / Brazzers.com] Faye Reagan","uid":5967408,"size":850024953,"categoryP":"porn","categoryS":"movies","magnet":"?xt=urn:btih:2e26e6be374219423ce2d7cdaf1a9b4fdeedb6a4&amp;dn=%5BBigTitsInUniform.com+%2F+Brazzers.com%5D+Faye+Reagan&amp;tr=udp%3A%2F%2Ftracker.openbittorrent.com%3A80&amp;tr=udp%3A%2F%2Fopen.demonii.com%3A1337&amp;tr=udp%3A%2F%2Ftracker.coppersurfer.tk%3A6969&amp;tr=udp%3A%2F%2Fexodus.desync.com%3A6969","seeders":1,"leechers":0,"uploader":"exmnova","files":5,"time":1290158788,"description":"[BigTitsInUniform.com / Brazzers.com] Faye Reagan\n\n &lt;a href=&quot; http://www.picswan.com/img/share.php?id=3253_4CE634C5&quot; rel=&quot;nofollow&quot; target=&quot;_NEW&quot;&gt; http://www.picswan.com/img/share.php?id=3253_4CE634C5&lt;/a&gt;\n\n &lt;a href=&quot; http://www.picswan.com/img/share.php?id=1976_4CE634C5&quot; rel=&quot;nofollow&quot; target=&quot;_NEW&quot;&gt; http://www.picswan.com/img/share.php?id=1976_4CE634C5&lt;/a&gt;","torrent":{"xt":"urn:btih:2e26e6be374219423ce2d7cdaf1a9b4fdeedb6a4","amp;dn":"%5BBigTitsInUniform.com+%2F+Brazzers.com%5D+Faye+Reagan","amp;tr":["udp%3A%2F%2Ftracker.openbittorrent.com%3A80","udp%3A%2F%2Fopen.demonii.com%3A1337","udp%3A%2F%2Ftracker.coppersurfer.tk%3A6969","udp%3A%2F%2Fexodus.desync.com%3A6969"],"infoHash":"2e26e6be374219423ce2d7cdaf1a9b4fdeedb6a4","infoHashBuffer":{"type":"Buffer","data":[46,38,230,190,55,66,25,66,60,226,215,205,175,26,155,79,222,237,182,164]},"announce":[],"urlList":[]}}