{"title":"[MonstersOfCock] Riley Reid - Riley Reid loves Black Dick (06.08","uid":8779814,"size":861429363,"categoryP":"porn","categoryS":"hd___movies","magnet":"?xt=urn:btih:2ef04f3f7ed5fdef7eb17190980a12ebab57fa39&amp;dn=%5BMonstersOfCock%5D+Riley+Reid+-+Riley+Reid+loves+Black+Dick+%2806.08&amp;tr=udp%3A%2F%2Ftracker.openbittorrent.com%3A80&amp;tr=udp%3A%2F%2Fopen.demonii.com%3A1337&amp;tr=udp%3A%2F%2Ftracker.coppersurfer.tk%3A6969&amp;tr=udp%3A%2F%2Fexodus.desync.com%3A6969","seeders":1,"leechers":0,"uploader":"xuluhulu","files":1,"time":1375652479,"description":"THUMBSNAIL SCREENS:\n\n &lt;a href=&quot;\nhttp://www.imgnip.com/viewer.php?file=19202714281788340658.jpg&quot; rel=&quot;nofollow&quot; target=&quot;_NEW&quot;&gt;\nhttp://www.imgnip.com/viewer.php?file=19202714281788340658.jpg&lt;/a&gt;\n\n\n\nSEED &amp; ENJOY!!!","torrent":{"xt":"urn:btih:2ef04f3f7ed5fdef7eb17190980a12ebab57fa39","amp;dn":"%5BMonstersOfCock%5D+Riley+Reid+-+Riley+Reid+loves+Black+Dick+%2806.08","amp;tr":["udp%3A%2F%2Ftracker.openbittorrent.com%3A80","udp%3A%2F%2Fopen.demonii.com%3A1337","udp%3A%2F%2Ftracker.coppersurfer.tk%3A6969","udp%3A%2F%2Fexodus.desync.com%3A6969"],"infoHash":"2ef04f3f7ed5fdef7eb17190980a12ebab57fa39","infoHashBuffer":{"type":"Buffer","data":[46,240,79,63,126,213,253,239,126,177,113,144,152,10,18,235,171,87,250,57]},"announce":[],"urlList":[]}}