{"title":"[youshikibi] Kana Nishino - Namidairo (1280x720 h264 AAC) [e1314","uid":8736039,"size":128326795,"categoryP":"video","categoryS":"music_videos","magnet":"?xt=urn:btih:4ae874521507bdd09e619387f2750ab760012f87&amp;dn=%5Byoushikibi%5D+Kana+Nishino+-+Namidairo+%281280x720+h264+AAC%29+%5Be1314&amp;tr=udp%3A%2F%2Ftracker.openbittorrent.com%3A80&amp;tr=udp%3A%2F%2Fopen.demonii.com%3A1337&amp;tr=udp%3A%2F%2Ftracker.coppersurfer.tk%3A6969&amp;tr=udp%3A%2F%2Fexodus.desync.com%3A6969","seeders":1,"leechers":0,"uploader":"youshikibi","files":-1,"time":1374685412,"description":"Artist: Kana Nishino\nMusic Video: Namidairo (Color of tears)\nGenre: Ballad\nRelease date: August 07, 2013\n\n\nscreenshots: &lt;a href=&quot;\nhttp://youshikibismusicblog.files.wordpress.com/2013/07/kana-nishino-namidairo-mp4_thumbs_2013-07-23_18-05-27.jpg&quot; rel=&quot;nofollow&quot; target=&quot;_NEW&quot;&gt;\nhttp://youshikibismusicblog.files.wordpress.com/2013/07/kana-nishino-namidairo-mp4_thumbs_2013-07-23_18-05-27.jpg&lt;/a&gt;\n\n\nmore stuuf at my website: &lt;a href=&quot;\nhttp://youshikibi.com/&quot; rel=&quot;nofollow&quot; target=&quot;_NEW&quot;&gt;\nhttp://youshikibi.com/&lt;/a&gt;","torrent":{"xt":"urn:btih:4ae874521507bdd09e619387f2750ab760012f87","amp;dn":"%5Byoushikibi%5D+Kana+Nishino+-+Namidairo+%281280x720+h264+AAC%29+%5Be1314","amp;tr":["udp%3A%2F%2Ftracker.openbittorrent.com%3A80","udp%3A%2F%2Fopen.demonii.com%3A1337","udp%3A%2F%2Ftracker.coppersurfer.tk%3A6969","udp%3A%2F%2Fexodus.desync.com%3A6969"],"infoHash":"4ae874521507bdd09e619387f2750ab760012f87","infoHashBuffer":{"type":"Buffer","data":[74,232,116,82,21,7,189,208,158,97,147,135,242,117,10,183,96,1,47,135]},"announce":[],"urlList":[]}}