{"title":"Here.Comes.Honey.Boo.Boo.S02E04.480p.HDTV.x264-mSD","uid":8776751,"size":133755379,"categoryP":"video","categoryS":"tv_shows","magnet":"?xt=urn:btih:4f279e0405e65bb1e71a24d5fcf66ab9de8d1ed0&amp;dn=Here.Comes.Honey.Boo.Boo.S02E04.480p.HDTV.x264-mSD&amp;tr=udp%3A%2F%2Ftracker.openbittorrent.com%3A80&amp;tr=udp%3A%2F%2Fopen.demonii.com%3A1337&amp;tr=udp%3A%2F%2Ftracker.coppersurfer.tk%3A6969&amp;tr=udp%3A%2F%2Fexodus.desync.com%3A6969","seeders":1,"leechers":0,"uploader":"TvTeam","files":4,"time":1375575609,"description":"::::::::::::::::::::::::::::::::::::::::::::::::::::::::::::::::::::::::::\n  &lt;a href=&quot;\nhttp://www.torrenting.com&quot; rel=&quot;nofollow&quot; target=&quot;_NEW&quot;&gt;\nhttp://www.torrenting.com&lt;/a&gt;\n\n::::::::::::::::::::::::::::::::::::::::::::::::::::::::::::::::::::::::::\n\n(((((((((((((= Enjoy No RAR releases =))))))))))))))))))))\n\n\nMust Try:  &lt;a href=&quot; http://www.torrenting.com&quot; rel=&quot;nofollow&quot; target=&quot;_NEW&quot;&gt; http://www.torrenting.com&lt;/a&gt;","torrent":{"xt":"urn:btih:4f279e0405e65bb1e71a24d5fcf66ab9de8d1ed0","amp;dn":"Here.Comes.Honey.Boo.Boo.S02E04.480p.HDTV.x264-mSD","amp;tr":["udp%3A%2F%2Ftracker.openbittorrent.com%3A80","udp%3A%2F%2Fopen.demonii.com%3A1337","udp%3A%2F%2Ftracker.coppersurfer.tk%3A6969","udp%3A%2F%2Fexodus.desync.com%3A6969"],"infoHash":"4f279e0405e65bb1e71a24d5fcf66ab9de8d1ed0","infoHashBuffer":{"type":"Buffer","data":[79,39,158,4,5,230,91,177,231,26,36,213,252,246,106,185,222,141,30,208]},"announce":[],"urlList":[]}}