{"title":"The Art Of Getting By [2011]BRRip XviD","uid":6842410,"size":1073281326,"categoryP":"video","categoryS":"movies","magnet":"?xt=urn:btih:55896e9fbf1004468b4a102c9e11f26c68dc9c57&amp;dn=The+Art+Of+Getting+By+%5B2011%5DBRRip+XviD&amp;tr=udp%3A%2F%2Ftracker.openbittorrent.com%3A80&amp;tr=udp%3A%2F%2Fopen.demonii.com%3A1337&amp;tr=udp%3A%2F%2Ftracker.coppersurfer.tk%3A6969&amp;tr=udp%3A%2F%2Fexodus.desync.com%3A6969","seeders":1,"leechers":0,"uploader":"rcbcsk","files":-1,"time":1322216774,"description":"===========Visit Extratorrent for more Exclusives==============\n\nVisit Extratorrent for more exclusives....\n\nExtratorrent a Complete FreeLeech Site!! Registrations are absolutely FREE!!\n\nRegister by visiting..... www.Extratorrent\n\n===========Visit Extratorrent for more Exclusives==============\n\n\n\n\nCovers\n\n\nScreen Shots\n &lt;a href=&quot;\nhttp://www.shotpix.com/images/53994199624232890532.png&quot; rel=&quot;nofollow&quot; target=&quot;_NEW&quot;&gt;\nhttp://www.shotpix.com/images/53994199624232890532.png&lt;/a&gt;\n &lt;a href=&quot;\nhttp://www.shotpix.com/images/99313802454768782193.png&quot; rel=&quot;nofollow&quot; target=&quot;_NEW&quot;&gt;\nhttp://www.shotpix.com/images/99313802454768782193.png&lt;/a&gt;\n &lt;a href=&quot;\nhttp://www.shotpix.com/images/51992280102190937604.png&quot; rel=&quot;nofollow&quot; target=&quot;_NEW&quot;&gt;\nhttp://www.shotpix.com/images/51992280102190937604.png&lt;/a&gt;","torrent":{"xt":"urn:btih:55896e9fbf1004468b4a102c9e11f26c68dc9c57","amp;dn":"The+Art+Of+Getting+By+%5B2011%5DBRRip+XviD","amp;tr":["udp%3A%2F%2Ftracker.openbittorrent.com%3A80","udp%3A%2F%2Fopen.demonii.com%3A1337","udp%3A%2F%2Ftracker.coppersurfer.tk%3A6969","udp%3A%2F%2Fexodus.desync.com%3A6969"],"infoHash":"55896e9fbf1004468b4a102c9e11f26c68dc9c57","infoHashBuffer":{"type":"Buffer","data":[85,137,110,159,191,16,4,70,139,74,16,44,158,17,242,108,104,220,156,87]},"announce":[],"urlList":[]}}