{"title":"Family Guy 05x03 HR PDTV AC3 5 1 XviD-CTU - Hell Comes to Q","uid":3529005,"size":239874122,"categoryP":"video","categoryS":"tv_shows","magnet":"?xt=urn:btih:58e1b49aec8fc053852188366407c4e31f7ee9fa&amp;dn=Family+Guy+05x03+HR+PDTV+AC3+5+1+XviD-CTU+-+Hell+Comes+to+Q&amp;tr=udp%3A%2F%2Ftracker.openbittorrent.com%3A80&amp;tr=udp%3A%2F%2Fopen.demonii.com%3A1337&amp;tr=udp%3A%2F%2Ftracker.coppersurfer.tk%3A6969&amp;tr=udp%3A%2F%2Fexodus.desync.com%3A6969","seeders":1,"leechers":0,"uploader":"whatthehey","files":-1,"time":1159159381,"description":"Family Guy 05x03 HR PDTV AC3 5 1 XviD-CTU - Hell Comes to Quahog avi","torrent":{"xt":"urn:btih:58e1b49aec8fc053852188366407c4e31f7ee9fa","amp;dn":"Family+Guy+05x03+HR+PDTV+AC3+5+1+XviD-CTU+-+Hell+Comes+to+Q","amp;tr":["udp%3A%2F%2Ftracker.openbittorrent.com%3A80","udp%3A%2F%2Fopen.demonii.com%3A1337","udp%3A%2F%2Ftracker.coppersurfer.tk%3A6969","udp%3A%2F%2Fexodus.desync.com%3A6969"],"infoHash":"58e1b49aec8fc053852188366407c4e31f7ee9fa","infoHashBuffer":{"type":"Buffer","data":[88,225,180,154,236,143,192,83,133,33,136,54,100,7,196,227,31,126,233,250]},"announce":[],"urlList":[]}}