{"title":"mulan .avi","uid":5912624,"size":722270208,"categoryP":"video","categoryS":"movies","magnet":"?xt=urn:btih:6041c60584b5f931ba286f50ef4e055f37ffb4ab&amp;dn=mulan+.avi&amp;tr=udp%3A%2F%2Ftracker.openbittorrent.com%3A80&amp;tr=udp%3A%2F%2Fopen.demonii.com%3A1337&amp;tr=udp%3A%2F%2Ftracker.coppersurfer.tk%3A6969&amp;tr=udp%3A%2F%2Fexodus.desync.com%3A6969","seeders":1,"leechers":0,"uploader":"fartou","files":1,"time":1288102860,"description":"RÃƒÂ©alisÃƒÂ© par Tony Bancroft, Barry Cook\nAvec Ming-Na Wen, Eddie Murphy, Miguel Ferrer, plus\n\nLong-mÃƒÂ©trage amÃƒÂ©ricain . Genre : Animation\nDurÃƒÂ©e : 01h28min AnnÃƒÂ©e de production : 1998\n\nSynopsis : Mulan est une belle jeune fille qui vit dans un village chinois. MalgrÃƒÂ© son amour et son respect pour sa famille, son mÃƒÂ©pris des conventions l'ÃƒÂ©loigne des rÃƒÂ´les dÃƒÂ©volus aux filles devouÃƒÂ©es. Quand son pays est envahi par les Huns, Mulan, n'ÃƒÂ©coutant que son courage, s'engage ÃƒÂ  la place de son pÃƒÂ¨re dans le but de lui sauver la vie. Elle va devenir, avec l'aide d'un dragon en quÃƒÂ¨te de rÃƒÂ©habilitation, un guerrier hors du commun.\n","torrent":{"xt":"urn:btih:6041c60584b5f931ba286f50ef4e055f37ffb4ab","amp;dn":"mulan+.avi","amp;tr":["udp%3A%2F%2Ftracker.openbittorrent.com%3A80","udp%3A%2F%2Fopen.demonii.com%3A1337","udp%3A%2F%2Ftracker.coppersurfer.tk%3A6969","udp%3A%2F%2Fexodus.desync.com%3A6969"],"infoHash":"6041c60584b5f931ba286f50ef4e055f37ffb4ab","infoHashBuffer":{"type":"Buffer","data":[96,65,198,5,132,181,249,49,186,40,111,80,239,78,5,95,55,255,180,171]},"announce":[],"urlList":[]}}