{"title":"The Comfortable Chair (1968) [FLAC]","uid":9440815,"size":188724982,"categoryP":"audio","categoryS":"flac","magnet":"?xt=urn:btih:868260eb27a114b9774fff633cc7d9344aa88d34&amp;dn=The+Comfortable+Chair+%281968%29+%5BFLAC%5D+&amp;tr=udp%3A%2F%2Ftracker.openbittorrent.com%3A80&amp;tr=udp%3A%2F%2Fopen.demonii.com%3A1337&amp;tr=udp%3A%2F%2Ftracker.coppersurfer.tk%3A6969&amp;tr=udp%3A%2F%2Fexodus.desync.com%3A6969","seeders":1,"leechers":1,"uploader":null,"files":22,"time":1389009006,"description":"The Comfortable Chair - The Comfortable Chair (1968)\n\nGenre: US, West Coast Sunny Psych\n\nTracklist:\n\n1. Ain't No Good No More - 2:35\n2. Child's Garden - 2:38\n3. I'll See You - 2:26\n4. Princess - 2:43\n5. Now - 2:56\n6. Some Soon Some Day - 3:10\n7. Be Me - 2:37\n8. Loved It All - 2:26\n9. Let Me Through - 2:19\n10.Stars In Heaven - 3:00\n11.Pale Night Of Quiet - 3:52\n12.The Beast (Kali Yuza) - 3:26\n\nPersonel:\n*Bernie Schwartz - Lead Vocals\n*Barbara &quot;Baczek&quot; Wallace - Vocals\n*Gene Garfin- Clarinet, Percussion, Vocals\n*Greg Leroy - Bass Guitar, Guitar\n*Warner Davis - Drums\n*Tad Baczek - Guitar\n","torrent":{"xt":"urn:btih:868260eb27a114b9774fff633cc7d9344aa88d34","amp;dn":"The+Comfortable+Chair+%281968%29+%5BFLAC%5D+","amp;tr":["udp%3A%2F%2Ftracker.openbittorrent.com%3A80","udp%3A%2F%2Fopen.demonii.com%3A1337","udp%3A%2F%2Ftracker.coppersurfer.tk%3A6969","udp%3A%2F%2Fexodus.desync.com%3A6969"],"infoHash":"868260eb27a114b9774fff633cc7d9344aa88d34","infoHashBuffer":{"type":"Buffer","data":[134,130,96,235,39,161,20,185,119,79,255,99,60,199,217,52,74,168,141,52]},"announce":[],"urlList":[]}}