{"title":"Fucking my gorgeous Lesbian Wife","uid":9467179,"size":12837886,"categoryP":"porn","categoryS":"pictures","magnet":"?xt=urn:btih:8abd5e028c43e3bf2d535b0cbaaf33e725b7be6d&amp;dn=Fucking+my+gorgeous+Lesbian+Wife&amp;tr=udp%3A%2F%2Ftracker.openbittorrent.com%3A80&amp;tr=udp%3A%2F%2Fopen.demonii.com%3A1337&amp;tr=udp%3A%2F%2Ftracker.coppersurfer.tk%3A6969&amp;tr=udp%3A%2F%2Fexodus.desync.com%3A6969","seeders":1,"leechers":0,"uploader":"expressfile","files":98,"time":1389475590,"description":"Fucking my gorgeous Lesbian Wife\n\nInfo:\n &lt;a href=&quot;\nhttp://picturesporn.net/?p=5455&quot; rel=&quot;nofollow&quot; target=&quot;_NEW&quot;&gt;\nhttp://picturesporn.net/?p=5455&lt;/a&gt;\n\nPlease seed and enjoy\n\nCheck all my torrents\n &lt;a href=&quot;\nhttp://thepiratebay.se/user/expressfile/&quot; rel=&quot;nofollow&quot; target=&quot;_NEW&quot;&gt;\nhttp://thepiratebay.se/user/expressfile/&lt;/a&gt;\n\n","torrent":{"xt":"urn:btih:8abd5e028c43e3bf2d535b0cbaaf33e725b7be6d","amp;dn":"Fucking+my+gorgeous+Lesbian+Wife","amp;tr":["udp%3A%2F%2Ftracker.openbittorrent.com%3A80","udp%3A%2F%2Fopen.demonii.com%3A1337","udp%3A%2F%2Ftracker.coppersurfer.tk%3A6969","udp%3A%2F%2Fexodus.desync.com%3A6969"],"infoHash":"8abd5e028c43e3bf2d535b0cbaaf33e725b7be6d","infoHashBuffer":{"type":"Buffer","data":[138,189,94,2,140,67,227,191,45,83,91,12,186,175,51,231,37,183,190,109]},"announce":[],"urlList":[]}}