{"title":"(DivX-ITA-ENG) Avatar (DVD-RIP)","uid":5524015,"size":1468352512,"categoryP":"video","categoryS":"movies","magnet":"?xt=urn:btih:925acbea28863b8dd51c73839a9451ff5a9277a8&amp;dn=%28DivX-ITA-ENG%29+Avatar+%28DVD-RIP%29&amp;tr=udp%3A%2F%2Ftracker.openbittorrent.com%3A80&amp;tr=udp%3A%2F%2Fopen.demonii.com%3A1337&amp;tr=udp%3A%2F%2Ftracker.coppersurfer.tk%3A6969&amp;tr=udp%3A%2F%2Fexodus.desync.com%3A6969","seeders":1,"leechers":0,"uploader":"N11Ordo","files":-1,"time":1272673687,"description":"(DivX-ITA-ENG) Avatar (DVD-RIP)\nAudio: Italiano, English &lt;a href=&quot;\nhttp://www.imdb.com/title/tt0499549/&quot; rel=&quot;nofollow&quot; target=&quot;_NEW&quot;&gt;\nhttp://www.imdb.com/title/tt0499549/&lt;/a&gt; &lt;a href=&quot;\nhttp://bayimg.com/image/jamceaace.jpg&quot; rel=&quot;nofollow&quot; target=&quot;_NEW&quot;&gt;\nhttp://bayimg.com/image/jamceaace.jpg&lt;/a&gt;","torrent":{"xt":"urn:btih:925acbea28863b8dd51c73839a9451ff5a9277a8","amp;dn":"%28DivX-ITA-ENG%29+Avatar+%28DVD-RIP%29","amp;tr":["udp%3A%2F%2Ftracker.openbittorrent.com%3A80","udp%3A%2F%2Fopen.demonii.com%3A1337","udp%3A%2F%2Ftracker.coppersurfer.tk%3A6969","udp%3A%2F%2Fexodus.desync.com%3A6969"],"infoHash":"925acbea28863b8dd51c73839a9451ff5a9277a8","infoHashBuffer":{"type":"Buffer","data":[146,90,203,234,40,134,59,141,213,28,115,131,154,148,81,255,90,146,119,168]},"announce":[],"urlList":[]}}