{"title":"Anawaty Russell - Ambient Universe, ambient post-rock","uid":9592616,"size":192372157,"categoryP":"audio","categoryS":"flac","magnet":"?xt=urn:btih:9eca44bd0c72b61dfc8308b4e59cb08fc87b6803&amp;dn=Anawaty+Russell+-+Ambient+Universe%2C+ambient+post-rock&amp;tr=udp%3A%2F%2Ftracker.openbittorrent.com%3A80&amp;tr=udp%3A%2F%2Fopen.demonii.com%3A1337&amp;tr=udp%3A%2F%2Ftracker.coppersurfer.tk%3A6969&amp;tr=udp%3A%2F%2Fexodus.desync.com%3A6969","seeders":1,"leechers":0,"uploader":"Cstudio","files":-1,"time":1391941792,"description":"Analog Universe is the 2nd Anawaty Russell album. It's a critically acclaimed, beautifully produced album that covers many genres yet remains entirely cohesive. \n\nSo it's great for driving, dinner parties, yoga, relaxing at home (with headphones especially), in a coffee shop in Amsterdam, or in Washington or Colorado USA. ;-)","torrent":{"xt":"urn:btih:9eca44bd0c72b61dfc8308b4e59cb08fc87b6803","amp;dn":"Anawaty+Russell+-+Ambient+Universe%2C+ambient+post-rock","amp;tr":["udp%3A%2F%2Ftracker.openbittorrent.com%3A80","udp%3A%2F%2Fopen.demonii.com%3A1337","udp%3A%2F%2Ftracker.coppersurfer.tk%3A6969","udp%3A%2F%2Fexodus.desync.com%3A6969"],"infoHash":"9eca44bd0c72b61dfc8308b4e59cb08fc87b6803","infoHashBuffer":{"type":"Buffer","data":[158,202,68,189,12,114,182,29,252,131,8,180,229,156,176,143,200,123,104,3]},"announce":[],"urlList":[]}}