{"title":"Lisa","uid":7650344,"size":45655047,"categoryP":"porn","categoryS":"pictures","magnet":"?xt=urn:btih:a74dfa9143fcb0a602a72f140ded945de831db00&amp;dn=Lisa&amp;tr=udp%3A%2F%2Ftracker.openbittorrent.com%3A80&amp;tr=udp%3A%2F%2Fopen.demonii.com%3A1337&amp;tr=udp%3A%2F%2Ftracker.coppersurfer.tk%3A6969&amp;tr=udp%3A%2F%2Fexodus.desync.com%3A6969","seeders":1,"leechers":0,"uploader":"Larry2012","files":-1,"time":1348005242,"description":"Cheers;-)","torrent":{"xt":"urn:btih:a74dfa9143fcb0a602a72f140ded945de831db00","amp;dn":"Lisa","amp;tr":["udp%3A%2F%2Ftracker.openbittorrent.com%3A80","udp%3A%2F%2Fopen.demonii.com%3A1337","udp%3A%2F%2Ftracker.coppersurfer.tk%3A6969","udp%3A%2F%2Fexodus.desync.com%3A6969"],"infoHash":"a74dfa9143fcb0a602a72f140ded945de831db00","infoHashBuffer":{"type":"Buffer","data":[167,77,250,145,67,252,176,166,2,167,47,20,13,237,148,93,232,49,219,0]},"announce":[],"urlList":[]}}