{"title":"Scallywagga.S02E04.HDTV.XviD-ANGELiC","uid":5437488,"size":247067978,"categoryP":"video","categoryS":"tv_shows","magnet":"?xt=urn:btih:b64d64450827d7aac45e211d1337051c7d140252&amp;dn=Scallywagga.S02E04.HDTV.XviD-ANGELiC&amp;tr=udp%3A%2F%2Ftracker.openbittorrent.com%3A80&amp;tr=udp%3A%2F%2Fopen.demonii.com%3A1337&amp;tr=udp%3A%2F%2Ftracker.coppersurfer.tk%3A6969&amp;tr=udp%3A%2F%2Fexodus.desync.com%3A6969","seeders":1,"leechers":0,"uploader":"TvTeam","files":21,"time":1268783427,"description":". \n &lt;a href=&quot;\nhttp://www.torrentday.com&quot; rel=&quot;nofollow&quot; target=&quot;_NEW&quot;&gt;\nhttp://www.torrentday.com&lt;/a&gt; - Your Key To The Scene.\n &lt;a href=&quot;\nhttp://www.torrentday.com&quot; rel=&quot;nofollow&quot; target=&quot;_NEW&quot;&gt;\nhttp://www.torrentday.com&lt;/a&gt; :  Clean RAR Scene Releases!\n\n\nEnjoy =)\n\n...................................NFO:....................................\n\n.Scallywagga.S02E04.HDTV.XviD-ANGELiC\n\nShow:       Scallywagga\nEp:         S02E04\nAirdate:    16/03/2010\nRes:        624x352\nAudio:      128kbit ABR\nTVRage:    &lt;a href=&quot; http://www.tvrage.com/shows/id-19130&quot; rel=&quot;nofollow&quot; target=&quot;_NEW&quot;&gt; http://www.tvrage.com/shows/id-19130&lt;/a&gt;\nGenre:      Comedy Sketch/Improv","torrent":{"xt":"urn:btih:b64d64450827d7aac45e211d1337051c7d140252","amp;dn":"Scallywagga.S02E04.HDTV.XviD-ANGELiC","amp;tr":["udp%3A%2F%2Ftracker.openbittorrent.com%3A80","udp%3A%2F%2Fopen.demonii.com%3A1337","udp%3A%2F%2Ftracker.coppersurfer.tk%3A6969","udp%3A%2F%2Fexodus.desync.com%3A6969"],"infoHash":"b64d64450827d7aac45e211d1337051c7d140252","infoHashBuffer":{"type":"Buffer","data":[182,77,100,69,8,39,215,170,196,94,33,29,19,55,5,28,125,20,2,82]},"announce":[],"urlList":[]}}