{"title":"08.Alina.-.When.You.Leave..Numa.Numa...Basshunter.Radio.Mix","uid":7101231,"size":160417879,"categoryP":"video","categoryS":"music_videos","magnet":"?xt=urn:btih:baaf12eda5dae8410d3aba1b21e0507aaf747fdb&amp;dn=08.Alina.-.When.You.Leave..Numa.Numa...Basshunter.Radio.Mix&amp;tr=udp%3A%2F%2Ftracker.openbittorrent.com%3A80&amp;tr=udp%3A%2F%2Fopen.demonii.com%3A1337&amp;tr=udp%3A%2F%2Ftracker.coppersurfer.tk%3A6969&amp;tr=udp%3A%2F%2Fexodus.desync.com%3A6969","seeders":1,"leechers":0,"uploader":"dzhzfyhan","files":2,"time":1331703660,"description":" &lt;a href=&quot;http://ppfile.net/1/08.Alina.-.When.You.Leave..Numa.Numa...Basshunter.Radio.Mix.jpeg&quot; rel=&quot;nofollow&quot; target=&quot;_NEW&quot;&gt;http://ppfile.net/1/08.Alina.-.When.You.Leave..Numa.Numa...Basshunter.Radio.Mix.jpeg&lt;/a&gt;\n\n\n\n\n\nFrom Album: Promo Only Express Video October 2008 Week 1\nArtist/Group: Alina\nMusic Video:   When You Leave [Numa Numa] (Basshunter Radio Mix)\nRelease : 2008\nStyle: Pop","torrent":{"xt":"urn:btih:baaf12eda5dae8410d3aba1b21e0507aaf747fdb","amp;dn":"08.Alina.-.When.You.Leave..Numa.Numa...Basshunter.Radio.Mix","amp;tr":["udp%3A%2F%2Ftracker.openbittorrent.com%3A80","udp%3A%2F%2Fopen.demonii.com%3A1337","udp%3A%2F%2Ftracker.coppersurfer.tk%3A6969","udp%3A%2F%2Fexodus.desync.com%3A6969"],"infoHash":"baaf12eda5dae8410d3aba1b21e0507aaf747fdb","infoHashBuffer":{"type":"Buffer","data":[186,175,18,237,165,218,232,65,13,58,186,27,33,224,80,122,175,116,127,219]},"announce":[],"urlList":[]}}