{"title":"12 Rock Zone [Mp3]","uid":7060783,"size":403178495,"categoryP":"audio","categoryS":"music","magnet":"?xt=urn:btih:c9b36406821d8e8b199cc2f86d90df409db3b125&amp;dn=12+Rock+Zone+%5BMp3%5D&amp;tr=udp%3A%2F%2Ftracker.openbittorrent.com%3A80&amp;tr=udp%3A%2F%2Fopen.demonii.com%3A1337&amp;tr=udp%3A%2F%2Ftracker.coppersurfer.tk%3A6969&amp;tr=udp%3A%2F%2Fexodus.desync.com%3A6969","seeders":1,"leechers":0,"uploader":"virana","files":-1,"time":1330341379,"description":"VA - Rock Zone (3 CD) - 2012\n0\naÃƒÂ±adir enlaces para este archivo\nCategoria: Musica\nGenero: Rock\n\nVA - Rock Zone (3 CD) (2012)\n2012 | Rock | MP3 320 Kbps | 02:43:49 | 384.5 MB\n\n\n\n\n\nCD1\n\n01 Coldrain - Die Tomorrow\n02 Disarmonia Mundi - Ties That Bind\n03 Trivium - In Waves\n04 Bring Me the Horizon - Chelsea Smile\n05 Soilwork - Observation Slave\n06 Adept - No Guts, No Glory\n07 Asking Alexandria - To The Stage\n08 Bullet for My Valentine - Hand of Blood\n09 Sonic Syndicate - Flashback\n10 Dead by April - Stronger\n11 Ill Nino - When It Cuts\n12 Caliban - We Are The Many\n13 Arch Enemy - Yesterday Is Dead And Gone\n14 All That Remains - This Calling\n15 The Unguided - Serenade of Guilt\n\nCD2\n\n01 Evanescence - What You Want\n02 Limp Bizkit - Gold Cobra\n03 Linkin Park - What I ve Done\n04 Disturbed - Decadence\n05 Hollywood Undead - Levitate\n06 Static-X - The Only\n07 Rise Against - Make It Stop (September s Children)\n08 There For Tomorrow - Sore Winner\n09 30 Seconds To Mars - This Is War\n10 Foo Fighters - Everlong\n11 Guano Apes - Open Your Eyes\n12 Papa Roach - One Track Mind\n13 Sick Puppies - You re Going Down\n14 Nickelback - When We Stand Together\n15 Stone Sour - Hesitate\n\nCD3\n\n01 The Offspring - The Kids Aren t Alright\n02 Anti-Flag - Broken Bones\n03 Blink-182 - Up All Night\n04 Zebrahead - Get Nice!\n05 Misfits - The Devil s Rain\n06 Sum 41 - Screaming Bloody Murder\n07 Yellowcard - The Sound Of You And Me\n08 Green Day - Holiday\n09 Billy Talent - Red Flag\n10 Man Overboard - Somethings Weird\n11 Fall Out Boy - Dance Dance\n12 Good Charlotte - Lifestyles Of The Rich And Famous\n13 Rise Against - The First Drop\n14 Vanilla Sky - Just Dance\n15 Simple Plan - You Suck At Love\n","torrent":{"xt":"urn:btih:c9b36406821d8e8b199cc2f86d90df409db3b125","amp;dn":"12+Rock+Zone+%5BMp3%5D","amp;tr":["udp%3A%2F%2Ftracker.openbittorrent.com%3A80","udp%3A%2F%2Fopen.demonii.com%3A1337","udp%3A%2F%2Ftracker.coppersurfer.tk%3A6969","udp%3A%2F%2Fexodus.desync.com%3A6969"],"infoHash":"c9b36406821d8e8b199cc2f86d90df409db3b125","infoHashBuffer":{"type":"Buffer","data":[201,179,100,6,130,29,142,139,25,156,194,248,109,144,223,64,157,179,177,37]},"announce":[],"urlList":[]}}