{"title":"Salem Al Fakir  Augustifamiljen - Who Wants To Live Forever, Und","uid":7072304,"size":60203168,"categoryP":"video","categoryS":"music_videos","magnet":"?xt=urn:btih:d5a3b64721b7b5c3778ad74c16f0f90dba1c330e&amp;dn=Salem+Al+Fakir++Augustifamiljen+-+Who+Wants+To+Live+Forever%2C+Und&amp;tr=udp%3A%2F%2Ftracker.openbittorrent.com%3A80&amp;tr=udp%3A%2F%2Fopen.demonii.com%3A1337&amp;tr=udp%3A%2F%2Ftracker.coppersurfer.tk%3A6969&amp;tr=udp%3A%2F%2Fexodus.desync.com%3A6969","seeders":1,"leechers":0,"uploader":"RosaMannen","files":1,"time":1330720691,"description":"Great perfomance from Swedish television.\n\n\n\n.ooOO ROSA MANNEN 2012 OOoo.\n                                                                                &lt;a href=&quot; http://thepiratebay.se/user/RosaMannen&quot; rel=&quot;nofollow&quot; target=&quot;_NEW&quot;&gt; http://thepiratebay.se/user/RosaMannen&lt;/a&gt;\t","torrent":{"xt":"urn:btih:d5a3b64721b7b5c3778ad74c16f0f90dba1c330e","amp;dn":"Salem+Al+Fakir++Augustifamiljen+-+Who+Wants+To+Live+Forever%2C+Und","amp;tr":["udp%3A%2F%2Ftracker.openbittorrent.com%3A80","udp%3A%2F%2Fopen.demonii.com%3A1337","udp%3A%2F%2Ftracker.coppersurfer.tk%3A6969","udp%3A%2F%2Fexodus.desync.com%3A6969"],"infoHash":"d5a3b64721b7b5c3778ad74c16f0f90dba1c330e","infoHashBuffer":{"type":"Buffer","data":[213,163,182,71,33,183,181,195,119,138,215,76,22,240,249,13,186,28,51,14]},"announce":[],"urlList":[]}}