{"title":"Edible Oil Processing from a Patent Perspective","uid":14577704,"size":10632251,"categoryP":"other","categoryS":"e_books","magnet":"?xt=urn:btih:db2b8d387b5d0eaeeed2b9e1b72fbf3f8648a524&amp;dn=Edible+Oil+Processing+from+a+Patent+Perspective&amp;tr=udp%3A%2F%2Ftracker.leechers-paradise.org%3A6969&amp;tr=udp%3A%2F%2Fzer0day.ch%3A1337&amp;tr=udp%3A%2F%2Fopen.demonii.com%3A1337&amp;tr=udp%3A%2F%2Ftracker.coppersurfer.tk%3A6969&amp;tr=udp%3A%2F%2Fexodus.desync.com%3A6969","seeders":1,"leechers":1,"uploader":"clouderone","files":1,"time":1462844302,"description":"Edible Oil Processing from a Patent Perspective - Albert J. Dijkstra (Springer, 2013).pdf\r\n\r\nISBN 978-1-4614-3350-7\r\n\r\nPatent literature has always been a mine of information, but until recently, it was difficult to access. Now, with the Internet, access to all patent documents is almost instantaneous and free. However, interpreting the technical information provided by patent literature requires a certain skill. This monograph aims to provide that skill by explaining patent jargon and providing background information on patenting.\r\n\r\nPatents dealing with edible oil processing are used to explain various aspects of patenting. To make the explanations less impersonal, some have been larded with personal remarks and experiences. Accordingly, this monograph is intended for scientists and engineers dealing with edible oils and fats who want to extend their sources of technical information. Hopefully, it will inspire them to innovate, help them to avoid duplication, and provide them with some amusement","torrent":{"xt":"urn:btih:db2b8d387b5d0eaeeed2b9e1b72fbf3f8648a524","amp;dn":"Edible+Oil+Processing+from+a+Patent+Perspective","amp;tr":["udp%3A%2F%2Ftracker.leechers-paradise.org%3A6969","udp%3A%2F%2Fzer0day.ch%3A1337","udp%3A%2F%2Fopen.demonii.com%3A1337","udp%3A%2F%2Ftracker.coppersurfer.tk%3A6969","udp%3A%2F%2Fexodus.desync.com%3A6969"],"infoHash":"db2b8d387b5d0eaeeed2b9e1b72fbf3f8648a524","infoHashBuffer":{"type":"Buffer","data":[219,43,141,56,123,93,14,174,238,210,185,225,183,47,191,63,134,72,165,36]},"announce":[],"urlList":[]}}