{"title":"[720p].SexoEnPublico.-.Katia.De.Lys","uid":7682347,"size":1153461248,"categoryP":"porn","categoryS":"hd___movies","magnet":"?xt=urn:btih:e7fa0d595226b7e0550132614832f202bd12e64f&amp;dn=%5B720p%5D.SexoEnPublico.-.Katia.De.Lys&amp;tr=udp%3A%2F%2Ftracker.openbittorrent.com%3A80&amp;tr=udp%3A%2F%2Fopen.demonii.com%3A1337&amp;tr=udp%3A%2F%2Ftracker.coppersurfer.tk%3A6969&amp;tr=udp%3A%2F%2Fexodus.desync.com%3A6969","seeders":1,"leechers":1,"uploader":"exmnova","files":1,"time":1348854139,"description":"[720p][SexoEnPublico./ Culioneros./ BangBros.] Katia De Lys (Huge ass gets fucked)\n\n\nWe ran into Katia, a Cuban mami with an ass that is a true work of art! Thin and with a beautiful pair of big natural tits, this chick was a fucking machine. She sucked Rober's cock on the patio of a beach house. After Rober was done fucking her, I was all hot so I jumped on her. I titty-fucked her and boned that pretty pussy hard until I couldn't stand it anymore and came in her face. Enjoy!\n\n\nScreens / More Info:\n\n\n &lt;a href=&quot;\nhttp://www.69bits.net/torrent/HD/59002/%5B720p%5D.SexoEnPublico.-.Katia.De.Lys.html&quot; rel=&quot;nofollow&quot; target=&quot;_NEW&quot;&gt;\nhttp://www.69bits.net/torrent/HD/59002/%5B720p%5D.SexoEnPublico.-.Katia.De.Lys.html&lt;/a&gt;","torrent":{"xt":"urn:btih:e7fa0d595226b7e0550132614832f202bd12e64f","amp;dn":"%5B720p%5D.SexoEnPublico.-.Katia.De.Lys","amp;tr":["udp%3A%2F%2Ftracker.openbittorrent.com%3A80","udp%3A%2F%2Fopen.demonii.com%3A1337","udp%3A%2F%2Ftracker.coppersurfer.tk%3A6969","udp%3A%2F%2Fexodus.desync.com%3A6969"],"infoHash":"e7fa0d595226b7e0550132614832f202bd12e64f","infoHashBuffer":{"type":"Buffer","data":[231,250,13,89,82,38,183,224,85,1,50,97,72,50,242,2,189,18,230,79]},"announce":[],"urlList":[]}}