{"title":"JacquieEtMichelTV - Ivana - Marie-Louise, sodomie iberique","uid":14936363,"size":577505816,"categoryP":"porn","categoryS":"movie_clips","magnet":"?xt=urn:btih:e8f575ea723cec4d30b335fb5949138448808ce9&amp;dn=JacquieEtMichelTV+-+Ivana+-+Marie-Louise%2C+sodomie+iberique&amp;tr=udp%3A%2F%2Ftracker.leechers-paradise.org%3A6969&amp;tr=udp%3A%2F%2Fzer0day.ch%3A1337&amp;tr=udp%3A%2F%2Fopen.demonii.com%3A1337&amp;tr=udp%3A%2F%2Ftracker.coppersurfer.tk%3A6969&amp;tr=udp%3A%2F%2Fexodus.desync.com%3A6969","seeders":1,"leechers":0,"uploader":"C47wh15p3r3r","files":1,"time":1466000487,"description":"JacquieEtMichelTV - Ivana - Marie-Louise, sodomie iberique\r\n\r\nScreenshots: \nhttp://www.imglocate.com/?v=470782 \nhttp://www.imglocate.com/?v=477677","torrent":{"xt":"urn:btih:e8f575ea723cec4d30b335fb5949138448808ce9","amp;dn":"JacquieEtMichelTV+-+Ivana+-+Marie-Louise%2C+sodomie+iberique","amp;tr":["udp%3A%2F%2Ftracker.leechers-paradise.org%3A6969","udp%3A%2F%2Fzer0day.ch%3A1337","udp%3A%2F%2Fopen.demonii.com%3A1337","udp%3A%2F%2Ftracker.coppersurfer.tk%3A6969","udp%3A%2F%2Fexodus.desync.com%3A6969"],"infoHash":"e8f575ea723cec4d30b335fb5949138448808ce9","infoHashBuffer":{"type":"Buffer","data":[232,245,117,234,114,60,236,77,48,179,53,251,89,73,19,132,72,128,140,233]},"announce":[],"urlList":[]}}