{"title":"Parni Valjak - Stvarno nestvarno 2011","uid":6771241,"size":37911026,"categoryP":"audio","categoryS":"music","magnet":"?xt=urn:btih:f86f7799e157f88c95875cdfdf2e7730603e5443&amp;dn=Parni+Valjak+-+Stvarno+nestvarno+2011&amp;tr=udp%3A%2F%2Ftracker.openbittorrent.com%3A80&amp;tr=udp%3A%2F%2Fopen.demonii.com%3A1337&amp;tr=udp%3A%2F%2Ftracker.coppersurfer.tk%3A6969&amp;tr=udp%3A%2F%2Fexodus.desync.com%3A6969","seeders":1,"leechers":0,"uploader":"mnvsi","files":10,"time":1319581872,"description":"01 - Nakon svih godina\n02 - Vjeruj\n03 - Svijet je danas lud\n04 - Za sve sam kriv sto nisam\n05 - Stvarno, nestvarno\n06 - Kralj iluzija\n07 - Aleluja (Ja jos vjerujem u nas)\n08 - Istina\n09 - Ljubav je droga\n10 - To sam stvarno ja\n\n\nBitrate: 128 kbps\n\n\nSeed!","torrent":{"xt":"urn:btih:f86f7799e157f88c95875cdfdf2e7730603e5443","amp;dn":"Parni+Valjak+-+Stvarno+nestvarno+2011","amp;tr":["udp%3A%2F%2Ftracker.openbittorrent.com%3A80","udp%3A%2F%2Fopen.demonii.com%3A1337","udp%3A%2F%2Ftracker.coppersurfer.tk%3A6969","udp%3A%2F%2Fexodus.desync.com%3A6969"],"infoHash":"f86f7799e157f88c95875cdfdf2e7730603e5443","infoHashBuffer":{"type":"Buffer","data":[248,111,119,153,225,87,248,140,149,135,92,223,223,46,119,48,96,62,84,67]},"announce":[],"urlList":[]}}